gatewayVoiceTesting/__init__.py
gatewayVoiceTesting/voiceTesting.py
gatewayVoiceTesting-1.0.0.dist-info/LICENSE
gatewayVoiceTesting-1.0.0.dist-info/METADATA
gatewayVoiceTesting-1.0.0.dist-info/WHEEL
gatewayVoiceTesting-1.0.0.dist-info/entry_points.txt
gatewayVoiceTesting-1.0.0.dist-info/top_level.txt
gatewayVoiceTesting-1.0.0.dist-info/RECORD
